CHANGES.rst
LICENSE
MANIFEST.in
README.rst
setup.cfg
setup.py
tox.ini
docs/CHANGES.rst
docs/README.rst
docs/conf.py
docs/index.rst
docs/install.rst
docs/intro.rst
docs/reference.rst
docs/tutorial.rst
docs/_static/.keep
docs/_templates/.keep
src/jt/__init__.py
src/jt/jpy.cfg
src/jt/jpyutil.py
src/jt/jpy/__about__.py
src/jt/jpy/__config__.py
src/jt/jpy/__init__.py
src/jt/jpy/_diag.py
src/jt/jpy/_jfield.py
src/jt/jpy/_verboseexcept.py
src/jt/jpy/_java/__init__.py
src/jt/jpy/_java/class2py.py
src/jt/jpy/_java/jnijpy.py
src/jt/jpy/_java/org/__init__.py
src/jt/jpy/_typehandler/__init__.py
src/jt/jpy_stdout/__init__.py
src/jtypes.jpy.egg-info/PKG-INFO
src/jtypes.jpy.egg-info/SOURCES.txt
src/jtypes.jpy.egg-info/dependency_links.txt
src/jtypes.jpy.egg-info/namespace_packages.txt
src/jtypes.jpy.egg-info/requires.txt
src/jtypes.jpy.egg-info/top_level.txt
src/jtypes.jpy.egg-info/zip-safe
tests/__init__.py
tests/__main__.py
tests/run.py
tests/z.py
tests/java/classes/org/jpy/DL.class
tests/java/classes/org/jpy/JavaReflectionTest.class
tests/java/classes/org/jpy/KeyError.class
tests/java/classes/org/jpy/LifeCycleTest.class
tests/java/classes/org/jpy/PyDictWrapper$1.class
tests/java/classes/org/jpy/PyDictWrapper$EntrySet$1$1.class
tests/java/classes/org/jpy/PyDictWrapper$EntrySet$1.class
tests/java/classes/org/jpy/PyDictWrapper$EntrySet.class
tests/java/classes/org/jpy/PyDictWrapper.class
tests/java/classes/org/jpy/PyInputMode.class
tests/java/classes/org/jpy/PyLib$CallableKind.class
tests/java/classes/org/jpy/PyLib$Diag.class
tests/java/classes/org/jpy/PyLib.class
tests/java/classes/org/jpy/PyLibConfig$OS.class
tests/java/classes/org/jpy/PyLibConfig.class
tests/java/classes/org/jpy/PyLibTest.class
tests/java/classes/org/jpy/PyLibWithSysPathTest.class
tests/java/classes/org/jpy/PyListWrapper$1.class
tests/java/classes/org/jpy/PyListWrapper.class
tests/java/classes/org/jpy/PyModule.class
tests/java/classes/org/jpy/PyModuleTest.class
tests/java/classes/org/jpy/PyObject.class
tests/java/classes/org/jpy/PyObjectTest$ISimple.class
tests/java/classes/org/jpy/PyObjectTest$ProcessorTask.class
tests/java/classes/org/jpy/PyObjectTest.class
tests/java/classes/org/jpy/StopIteration.class
tests/java/classes/org/jpy/UseCases.class
